setup.py
pluginplot/__init__.py
pluginplot/plot.py
pluginplot/plugin.py
pluginplot.egg-info/PKG-INFO
pluginplot.egg-info/SOURCES.txt
pluginplot.egg-info/dependency_links.txt
pluginplot.egg-info/not-zip-safe
pluginplot.egg-info/top_level.txt