Metadata-Version: 1.1
Name: pluginplot
Version: 0.1.0
Summary: Yet another simple plugin system for Python like WordPress plugin system
Home-page: https://github.com/zeuxisoo/python-pluginplot
Author: Zeuxis Lo
Author-email: seekstudio@gmail.com
License: BSD
Platform: any
Classifier: Development Status :: 4 - Beta
Classifier: License :: OSI Approved :: BSD License
Classifier: Programming Language :: Python
Classifier: Programming Language :: Python :: 2
Classifier: Programming Language :: Python :: 2.7
